abi_agents/__init__.py
abi_agents/orchestrator/Dockerfile
abi_agents/orchestrator/README.md
abi_agents/orchestrator/requirements.txt
abi_agents/orchestrator/agent/main.py
abi_agents/orchestrator/agent/orchestrator.py
abi_agents/orchestrator/agent/web_interface.py
abi_agents/orchestrator/agent/config/__init__.py
abi_agents/orchestrator/agent/config/config.py
abi_agents/orchestrator/agent/models/__init__.py
abi_agents/orchestrator/agent/models/outputs_model.py
abi_agents/planner/Dockerfile
abi_agents/planner/README.md
abi_agents/planner/requirements.txt
abi_agents/planner/agent/main.py
abi_agents/planner/agent/planner.py
abi_agents/planner/agent/config/__init__.py
abi_agents/planner/agent/config/config.py
abi_agents/planner/agent/models/__init__.py
abi_agents/planner/agent/models/agent_models.py
abi_cli/__init__.py
abi_cli/cli/README.md
abi_cli/cli/__init__.py
abi_cli/cli/banner.py
abi_cli/cli/main.py
abi_cli/cli/commands/__init__.py
abi_cli/cli/commands/add.py
abi_cli/cli/commands/create.py
abi_cli/cli/commands/info.py
abi_cli/cli/commands/provision.py
abi_cli/cli/commands/remove.py
abi_cli/cli/commands/run.py
abi_cli/cli/commands/status.py
abi_cli/cli/commands/utils.py
abi_cli/scaffolding/agent/Dockerfile.j2
abi_cli/scaffolding/agent/__init__.py
abi_cli/scaffolding/agent/agent.py.j2
abi_cli/scaffolding/agent/main.py.j2
abi_cli/scaffolding/agent/models.py.j2
abi_cli/scaffolding/agent/requirements.txt.j2
abi_cli/scaffolding/agent/common/__init__.py.j2
abi_cli/scaffolding/agent/common/a2a_server.py.j2
abi_cli/scaffolding/agent/common/agent_executor.py.j2
abi_cli/scaffolding/agent/common/prompts.py.j2
abi_cli/scaffolding/agent/common/utils.py.j2
abi_cli/scaffolding/agent/config/__init__.py.j2
abi_cli/scaffolding/agent/config/config.py.j2
abi_cli/scaffolding/common/web_interface.py.j2
abi_cli/scaffolding/project/.env.example
abi_cli/scaffolding/project/Dockerfile.j2
abi_cli/scaffolding/project/README.md.j2
abi_cli/scaffolding/project/__init__.py
abi_core_ai-1.5.11.dist-info/licenses/LICENSE
abi_core_ai-1.5.11.dist-info/METADATA
abi_core_ai-1.5.11.dist-info/WHEEL
abi_core_ai-1.5.11.dist-info/entry_points.txt
abi_core_ai-1.5.11.dist-info/top_level.txt
abi_core_ai-1.5.11.dist-info/RECORD
