Metadata-Version: 2.4
Name: abi-core-ai
Version: 1.5.11
Summary: Agent-Based Infrastructure Core - Runtime and CLI
Author-email: José Luis Martínez Abundiz <jl.mrtz@gmail.com>
License-Expression: Apache-2.0
Project-URL: Homepage, https://github.com/Joselo-zn/abi-core
Project-URL: Documentation, https://abi-core.readthedocs.io
Project-URL: Repository, https://github.com/Joselo-zn/abi-core
Project-URL: Issues, https://github.com/Joselo-zn/abi-core/issues
Project-URL: Changelog, https://github.com/Joselo-zn/abi-core/blob/main/CHANGELOG.md
Keywords: ai,agents,infrastructure,semantic,security
Classifier: Development Status :: 4 - Beta
Classifier: Intended Audience :: Developers
Classifier: Programming Language :: Python :: 3
Classifier: Programming Language :: Python :: 3.11
Classifier: Programming Language :: Python :: 3.12
Classifier: Topic :: Software Development :: Libraries :: Python Modules
Classifier: Topic :: Scientific/Engineering :: Artificial Intelligence
Requires-Python: >=3.11
License-File: LICENSE
Requires-Dist: click>=8.0.0
Requires-Dist: rich>=13.0.0
Requires-Dist: jinja2>=3.1.0
Requires-Dist: pyyaml>=6.0.0
Requires-Dist: pydantic>=2.0.0
Requires-Dist: langchain>=0.1.0
Requires-Dist: langchain-core>=0.2.20
Requires-Dist: langchain-ollama>=0.1.0
Requires-Dist: langchain-community>=0.1.0
Requires-Dist: langgraph>=0.1.0
Requires-Dist: fastapi>=0.100.0
Requires-Dist: uvicorn>=0.20.0
Requires-Dist: starlette>=0.27.0
Requires-Dist: requests>=2.31.0
Requires-Dist: httpx>=0.25.0
Requires-Dist: aiohttp>=3.8.0
Requires-Dist: a2a-sdk
Requires-Dist: mcp
Requires-Dist: fastmcp>=0.1.0
Requires-Dist: mcp-toolbox
Requires-Dist: networkx>=3.0.0
Requires-Dist: numpy>=1.24.0
Requires-Dist: redis>=4.5.0
Requires-Dist: tinydb>=4.7.0
Requires-Dist: psutil>=5.9.0
Provides-Extra: dev
Requires-Dist: pytest>=7.4.0; extra == "dev"
Requires-Dist: pytest-asyncio>=0.21.0; extra == "dev"
Requires-Dist: black>=23.0.0; extra == "dev"
Requires-Dist: ruff>=0.1.0; extra == "dev"
Requires-Dist: mypy>=1.5.0; extra == "dev"
Provides-Extra: semantic
Requires-Dist: weaviate-client>=4.0.0; extra == "semantic"
Requires-Dist: numpy>=1.24.0; extra == "semantic"
Provides-Extra: security
Requires-Dist: opa-python-client>=1.0.0; extra == "security"
Requires-Dist: cryptography>=41.0.0; extra == "security"
Dynamic: license-file
